practice/xor4.sv
module xor4(input  logic [3:0] a,
            output logic y);
    assign y = ^a;
endmodule

practice/tb_xor4.sv
module tb_xor4();
	logic [3:0] a;
    logic y, yexpected;
    logic clk, reset;
	logic [31:0] vectornum, errors;
	logic [4:0] testvectors[10000:0];
	
	// instantiate device under test
	xor4 dut(a, y);
	
	// generate clock
	always
		begin
			clk = 1; #5; clk = 0; #5;
		end
	
	// at start of test, load vectors
	// and pulse reset
	initial
		begin
            $dumpfile("xor4.vcd");
            $dumpvars(0, tb_xor4);

			$readmemb("xor4tb.txt", testvectors);
			vectornum = 0; errors = 0;
			reset = 1; #22; reset = 0;
		end
		
	// apply test vectors on rising edge of clk
	always @(posedge clk)
		begin
			#1; {a, yexpected} = testvectors[vectornum];
		end
		
	// check results on falling edge of clk
	always @(negedge clk)
		if (~reset) begin // skip during reset
			if (y !== yexpected) begin // check result
				$display("Error inputs = %b", a);
				$display(" outputs = %b (%b expected)", y, 
                         yexpected);
				errors = errors + 1;
			end
			vectornum = vectornum + 1;
            if (vectornum == 16) begin
				$display("%d tests completed with %d errors",
				         vectornum, errors);
            $finish;
	    	end
		end
endmodule

practice/xor4.vcd
$version Generated by VerilatedVcd $end
$timescale 1ps $end
 $scope module tb_xor4 $end
  $var wire 4 " a [3:0] $end
  $var wire 1 # y $end
  $var wire 1 $ yexpected $end
  $var wire 1 % clk $end
  $var wire 1 & reset $end
  $var wire 32 ' vectornum [31:0] $end
  $var wire 32 ( errors [31:0] $end
  $scope module dut $end
   $var wire 4 " a [3:0] $end
   $var wire 1 # y $end
  $upscope $end
 $upscope $end
$enddefinitions $end


#0
b0000 "
0#
0$
1%
1&
b00000000000000000000000000000000 '
b00000000000000000000000000000000 (
#5
0%
#10
1%
#15
0%
#20
1%
#22
0&
#25
0%
b00000000000000000000000000000001 '
#30
1%
#31
b0001 "
1#
1$
#35
0%
b00000000000000000000000000000010 '
#40
1%
#41
b0010 "
#45
0%
b00000000000000000000000000000011 '
#50
1%
#51
b0011 "
0#
0$
#55
0%
b00000000000000000000000000000100 '
#60
1%
#61
b0100 "
1#
#65
0%
b00000000000000000000000000000101 '
b00000000000000000000000000000001 (
#70
1%
#71
b0101 "
0#
#75
0%
b00000000000000000000000000000110 '
#80
1%
#81
b0110 "
#85
0%
b00000000000000000000000000000111 '
#90
1%
#91
b0111 "
1#
1$
#95
0%
b00000000000000000000000000001000 '
#100
1%
#101
b1000 "
#105
0%
b00000000000000000000000000001001 '
#110
1%
#111
b1001 "
0#
0$
#115
0%
b00000000000000000000000000001010 '
#120
1%
#121
b1010 "
#125
0%
b00000000000000000000000000001011 '
#130
1%
#131
b1011 "
1#
1$
#135
0%
b00000000000000000000000000001100 '
#140
1%
#141
b1100 "
0#
0$
#145
0%
b00000000000000000000000000001101 '
#150
1%
#151
b1101 "
1#
1$
#155
0%
b00000000000000000000000000001110 '
#160
1%
#161
b1110 "
#165
0%
b00000000000000000000000000001111 '
#170
1%
#171
b1111 "
0#
0$
#175
0%
b00000000000000000000000000010000 '
